{
  "$ref": "#/definitions/integration",
  "definitions": {
    "integration": {
      "type": "object",
      "properties": {
        "title": {
          "type": "string"
        },
        "date": {
          "anyOf": [
            {
              "type": "string",
              "format": "date-time"
            },
            {
              "type": "string",
              "format": "date"
            },
            {
              "type": "integer",
              "format": "unix-time"
            }
          ]
        },
        "description": {
          "type": "string"
        },
        "image": {
          "type": "string"
        },
        "draft": {
          "type": "boolean"
        },
        "meta_title": {
          "type": "string"
        },
        "meta_description": {
          "type": "string"
        },
        "robots": {
          "type": "string"
        },
        "exclude_from_sitemap": {
          "type": "boolean"
        },
        "custom_slug": {
          "type": "string"
        },
        "canonical": {
          "type": "string"
        },
        "keywords": {
          "type": "array",
          "items": {
            "type": "string"
          }
        },
        "disable_tagline": {
          "type": "boolean"
        },
        "categories": {
          "type": "array",
          "items": {
            "type": "string"
          }
        },
        "excerpt": {
          "type": "string"
        },
        "cta_btn": {
          "type": "object",
          "properties": {
            "enable": {
              "type": "boolean"
            },
            "label": {
              "type": "string"
            },
            "url": {
              "type": "string"
            },
            "rel": {
              "type": "string"
            },
            "target": {
              "type": "string"
            }
          },
          "required": [
            "enable",
            "label",
            "url"
          ],
          "additionalProperties": false
        },
        "sections": {
          "type": "array",
          "items": {
            "type": "object",
            "properties": {
              "title": {
                "type": "string"
              },
              "description": {
                "type": "string"
              },
              "category": {
                "type": "string"
              }
            },
            "required": [
              "title",
              "description",
              "category"
            ],
            "additionalProperties": false
          }
        },
        "fields": {
          "type": "array",
          "items": {
            "type": "object",
            "properties": {
              "name": {
                "type": "string"
              },
              "content": {
                "type": "string"
              }
            },
            "required": [
              "name",
              "content"
            ],
            "additionalProperties": false
          }
        },
        "$schema": {
          "type": "string"
        }
      },
      "required": [
        "title"
      ],
      "additionalProperties": false
    }
  },
  "$schema": "http://json-schema.org/draft-07/schema#"
}